{"id": 137326, "slug": "plutoku", "name": "Pluto(ku)", "name_original": "Pluto(ku)", "description": "<p>Game mod of Sudoku, made in a team of students for a class in three weeks</p>", "metacritic": null, "released": "2015-02-21", "tba": false, "updated": "2019-01-09T12:41:06", "background_image": "https://media.rawg.io/media/screenshots/f14/f141c16b8c87c99b9d969bd0fb1e7cff.jpg", "website": "", "rating": 0.0, "rating_top": 0, "added_by_status": null, "playtime": 0, "achievements_count": 0, "ratings_count": 0, "suggestions_count": 14, "game_series_count": 0, "reviews_count": 0, "platforms": [], "developers": ["mel"], "genres": ["Puzzle"], "publishers": [], "esrb_rating": null}