{"id": 180362, "slug": "blobville", "name": "Blobville", "name_original": "Blobville", "description": "<p>Blobville is a game about saving a near extinct tribe of Blobs called the Cyblobs.\u00a0<br/>Satisfy their needs to keep them happy and watch the village grow.</p>\n<p>~ Controls ~<br/>Mouse to select items, drop them and advance text<br/>Keyboard 1, 2 and 3 to select items</p>\n<p>~ Special thanks to ~<br/>My amazing testers M\u00f6r, Dani and Danny</p>\n<p>**~ Tools used ~**\u00a0\u00a0<br/>Unity, Visual Studio, GIMP, Audacity, FL Studio (VSTs: SpicyGuitar, DSK Overture), jfxr</p>\n<p>Created within 48h for Ludum Dare 40, (Theme: The more you have, the worse it is)</p>", "metacritic": null, "released": "2017-12-03", "tba": false, "updated": "2019-01-09T12:41:06", "background_image": "https://media.rawg.io/media/screenshots/935/935dd1a8042294d0ee2844abc64892de.jpg", "website": "", "rating": 0.0, "rating_top": 0, "added_by_status": null, "playtime": 0, "achievements_count": 0, "ratings_count": 0, "suggestions_count": 7, "game_series_count": 0, "reviews_count": 0, "platforms": ["PC", "macOS", "Linux", "Web"], "developers": ["Erkberg"], "genres": ["Strategy", "Simulation"], "publishers": [], "esrb_rating": null}