{"id": 195500, "slug": "puzzle-game-komilll", "name": "Puzzle game (komilll)", "name_original": "Puzzle game (komilll)", "description": "<p>Celem gry jest sprawienie, aby wszystkie kulki poza jedn\u0105 by\u0142y za\u015bwiecone. Klikaj\u0105c na kulk\u0119 zaczynaj\u0105 si\u0119 za\u015bwiecaj\u0105 si\u0119 lub gasn\u0105 wszystkie kulki z ni\u0105 po\u0142\u0105czone, a sama kulka w momencie klikni\u0119cia pozostaje zgaszona bez wzgl\u0119du na sw\u00f3j obecny stan.</p><p>Tr\u00f3jk\u0105t oznacza kulk\u0119 kt\u00f3ra jest w uk\u0142adzie traktowana jako prze\u017aroczysta - przekazuje \u0142adunek dalej. Mo\u017cna j\u0105 w\u0142\u0105czy\u0107 z powrotem klikaj\u0105c w tr\u00f3jk\u0105t.</p><p>Przekre\u015blenie oznacza kulk\u0119, kt\u00f3rej nie mo\u017cna klikn\u0105\u0107.</p><p>Liczba przy kulce oznacza pozosta\u0142\u0105 liczb\u0119 klikni\u0119\u0107.</p><p>\u017b\u00f3\u0142te kreski oznaczaj\u0105 po\u0142\u0105czeni z kulk\u0105, kt\u00f3re potrzebuje okre\u015blonej ilo\u015bci \u0142adunk\u00f3w do zapalenia si\u0119.</p><p>Czerwone/zielone to obecnie aktywne po\u0142\u0105czenia, kt\u00f3re zmieniaj\u0105 si\u0119 przy klikaniu g\u0142\u00f3wnej kulki.<br/></p><p>LPM - klikanie na kulki</p><p>R - restartowanie poziomu</p><p>Esc - powr\u00f3t do menu<br/></p>", "metacritic": null, "released": "2017-02-13", "tba": false, "updated": "2019-01-09T12:41:06", "background_image": "https://media.rawg.io/media/screenshots/1a7/1a7405bd45a588744feeb454415f768c.jpg", "website": "", "rating": 0.0, "rating_top": 0, "added_by_status": null, "playtime": 0, "achievements_count": 0, "ratings_count": 0, "suggestions_count": 20, "game_series_count": 0, "reviews_count": 0, "platforms": ["PC", "Web"], "developers": ["komilll"], "genres": ["Puzzle"], "publishers": [], "esrb_rating": null}