{"id": 207081, "slug": "gem-collector-ghostdreamer", "name": "Gem Collector (Ghostdreamer)", "name_original": "Gem Collector (Ghostdreamer)", "description": "<p>Gem Collector (Ghostdreamer) is a game developed by Ghostdreamer. It came out on 27-01-2016. <br>Gem Collector (Ghostdreamer) is available on PC, macOS, Linux and Web. You can purchase the game on itch.io. </p>\n\n<p></p>", "metacritic": null, "released": "2016-01-27", "tba": false, "updated": "2019-01-09T12:41:06", "background_image": "https://media.rawg.io/media/screenshots/cba/cba1c7b2db287d8142a985dee2755692.jpg", "website": "", "rating": 0.0, "rating_top": 0, "added_by_status": null, "playtime": 0, "achievements_count": 0, "ratings_count": 0, "suggestions_count": 56, "game_series_count": 0, "reviews_count": 0, "platforms": ["PC", "macOS", "Linux", "Web"], "developers": ["Ghostdreamer"], "genres": [], "publishers": [], "esrb_rating": null}