{"id": 235924, "slug": "the-terminal-1", "name": "The Terminal 1", "name_original": "The Terminal 1", "description": "The Game:<br/><br/>'The Terminal' game series first episode was created back in 2012. Original idea was to create a more realistic airport management game. Land, park, unload, load, fuel and take off your fleet. The better you play the more planes you get every game-day. Expand your airport with more jetways, runways and with an international terminal.<br/><br/>'The Terminal 1' is the original version of our world-popular 'The Terminal 2'. This version was originally designed for tablet screen-size so please buy it for larger screened devices only. Now you can again play with the original version airport management game with all the cute elements in it but limited functions. It seems now that this version will not have any bug fixes or improvements it has been released again for all of you who was missing the older style of gameplay. Enjoy the game and support us by purchasing the old version as well. <br/><br/>WalkThrough of the Original version:<br/>https://www.youtube.com/watch?v=qOENDRlSnYk<br/><br/>Main features of the original verison:<br/>- Be a super airport management game player, <br/>- Click to the Control Tower to see your planes in the near regions, <br/>- To send back your Tanker vehicles simple click them after fully tanked your jets,<br/>- For take off simple click on the planes when they are on the tarmac waiting for take off,<br/>- Expand your airplane fleet, your airport size, your passenger numbers by building more parking facilities from the Store menu,<br/>- Work as an airport manager, clear runways, take off planes, land your fleet,<br/>- Build new airplanes, create large airports, start new airplane routes, express yourself in the aviation market,<br/>- Enjoy the airport tycoon game experience, <br/>- Learn more about aviation tycoon games, <br/><br/>Promotional video: http://www.youtube.com/watch?v=ClVY277LowU&amp;feature=youtu.be<br/><br/>For community: Like us on Facebook at: www.facebook.com/theterminalgame<br/><br/>Game Development History:<br/>-------------------------------<br/>I always loved \"Flight games\" but always I was missing some more realistic graphics. So in October 2012, I decided to create a game for myself and also for the masses of You. Hope you will enjoy playing this game as much as I enjoyed creating it...", "metacritic": null, "released": "2014-08-10", "tba": false, "updated": "2019-07-30T13:45:09", "background_image": "https://media.rawg.io/media/screenshots/ce2/ce2e397220436e17b6db69e2f9569329.jpg", "website": "http://www.framelinenetwork.com", "rating": 0.0, "rating_top": 0, "added_by_status": null, "playtime": 0, "achievements_count": 0, "ratings_count": 0, "suggestions_count": 175, "game_series_count": 0, "reviews_count": 0, "platforms": ["iOS"], "developers": ["FrameLineNetwork Kft."], "genres": ["Strategy", "Simulation"], "publishers": ["FrameLineNetwork Kft."], "esrb_rating": null}