{"id": 257821, "slug": "the-testimony-of-trixie-glimmer-smith", "name": "The Testimony of Trixie Glimmer Smith", "name_original": "The Testimony of Trixie Glimmer Smith", "description": "<p>After finding the cursed play <em>'The King in Yellow'</em>, Trixie Glimmer Smith, a slacking student at Bluebell University recounts the terrible events that set her a week behind in her coursework.<br/></p>\n<p>This story follows on from the events of <em>Parsnip (free download here)</em>\u00a0with a host of new characters and an expanded world, although you can still enjoy it without playing <em>Parsnip.</em></p><p>Trixie is around 3-5 hours long, if you want to play all the content.</p>\n<p><strong>Check out the free demo below!</strong></p>\n<p><strong><em>Features</em></strong></p>\n<p><strong>Insight:</strong></p>\n\n<ul><li>Throughout the game events may start to take their toll on Trixie's mind. As Trixie gains insight her narration becomes ever more unreliable.</li><li>Unlike many sanity systems Trixie's insight system is hidden, meaning you never know for sure when you are being affected by it.</li><li>This system also means additional playthroughs of the game may vary! <em><br/><br/><strong>Can you really trust anything Trixie sees? Can you afford not to?</strong></em></li></ul>\n<p><strong>Multiple Paths:</strong></p>\n\n<ul><li>Trixie can choose to spend her week with the Friendly, albeit slightly scary shopkeeper Heidi, the excitable baker Gregg or the chill milkwoman Bell.</li><li>At points the three routes may intertwine, giving\u00a0different perspectives on the same story.</li><li>The game also has two main potential endings, with additional minor alternate endings.</li></ul>\n<p><strong>A Strange World:</strong></p>\n\n<ul><li>Set in a world of anthropomorphic animals, psychic birds and cosmic gods, Trixie explores the rural England inspired Bluefields County and discovers some of the horrors that secretly lurk in it's scenic countryside.</li></ul>\n<p><strong>Art Book:</strong></p>\n\n<ul><li>If you spend $6.99 on Trixie you get an Art book with the game! Exciting stuff! It contains all sorts of concept art,\u00a0 bios and fun trivia about the game, the characters and the world.</li></ul>\n\n<p><strong>Content Warnings:</strong></p>\n<p>Trixie Glimmer Smith contains a few mild descriptions of violence, horror, some exploration of negative trans feelings and some bad language.</p>\n<p><strong>E Begging:</strong></p>\n<p>If you enjoy Trixie please consider helping me out on Patreon!</p>\n<p>https://www.patreon.com/digitalpoppy</p>", "metacritic": null, "released": "2018-10-25", "tba": false, "updated": "2023-03-10T00:08:25", "background_image": "https://media.rawg.io/media/screenshots/2fc/2fc61319f1db561ff389724ae46c1179.jpg", "website": "", "rating": 0.0, "rating_top": 0, "added_by_status": {"yet": 3, "owned": 1, "beaten": 1, "dropped": 1}, "playtime": 0, "achievements_count": 0, "ratings_count": 2, "suggestions_count": 100, "game_series_count": 0, "reviews_count": 2, "platforms": ["PC", "macOS", "Linux"], "developers": ["Digital Poppy", "Bun & Birb", "MezmeroMania"], "genres": [], "publishers": [], "esrb_rating": null}