{"id": 302508, "slug": "pulchiosanter", "name": "Pulchiosanter", "name_original": "Pulchiosanter", "description": "<p>Pulchiosanter ist eine friedliche Parallelwelt, in der legend\u00e4re Krieger - sogenannte Elementarkrieger leben und f\u00fcr Frieden auf der Erde sorgen.</p>\n<p>Doch dieser Frieden scheint nicht von endloser Dauer zu sein.</p>\n<p>Der Sturm- und der Erdkrieger wurden von einem Geist des Neids befallen und schaden nun mehr, als dass sie f\u00fcr Recht und Ordnung einstehen.</p>\n<p>Kann es Light - der Anf\u00fchrer der Elemetarkrieger - zusammen mit seinen Br\u00fcdern bew\u00e4ltigen, sie wieder zur Vernunft zu bringen?<br/><br/><br/></p>", "metacritic": null, "released": "2019-03-17", "tba": false, "updated": "2019-03-18T02:29:30", "background_image": "https://media.rawg.io/media/screenshots/011/01130f41b77ab83909582d97cfd437d4.jpg", "website": "", "rating": 0.0, "rating_top": 0, "added_by_status": null, "playtime": 0, "achievements_count": 0, "ratings_count": 0, "suggestions_count": 79, "game_series_count": 0, "reviews_count": 0, "platforms": ["PC"], "developers": ["Pulchiosanter"], "genres": ["RPG"], "publishers": [], "esrb_rating": null}