{"id": 304684, "slug": "earth-advisor", "name": "Earth Advisor", "name_original": "Earth Advisor", "description": "<p>This is an experience for the Eden Holland park in the Netherlands.<br/><br/>There are two applications you need to run.<br/>The Panorama needs to be run on a Windows computer with a webcam.<br/>The Mobile version can only run on an Android phone with GPS and internet.<br/>Please note that this experience works best at the HKU location of G&amp;I.<br/><br/>Walk the route on the screen. At the end ask for your QR code in the mobile app. Once arrived at the Panorama, scan your QR code at the Panorama and enjoy the view.</p>", "metacritic": null, "released": "2019-03-26", "tba": false, "updated": "2019-03-29T04:32:08", "background_image": "https://media.rawg.io/media/screenshots/620/62061197e3d56243527c8f9748ed3cf2.jpg", "website": "", "rating": 0.0, "rating_top": 0, "added_by_status": null, "playtime": 0, "achievements_count": 0, "ratings_count": 0, "suggestions_count": 2, "game_series_count": 0, "reviews_count": 0, "platforms": ["PC", "Android"], "developers": ["NVriezen"], "genres": ["Educational"], "publishers": [], "esrb_rating": null}