{"id": 338082, "slug": "equilibrium-david-lopez", "name": "Equilibrium (David L\u00f3pez)", "name_original": "Equilibrium (David L\u00f3pez)", "description": "<p>Tap the screen trying to split the rectangles in half. Get the highest score before avoiding the duck colliding with the bushes.</p>", "metacritic": null, "released": "2019-06-29", "tba": false, "updated": "2019-07-01T04:50:19", "background_image": "https://media.rawg.io/media/screenshots/7d2/7d28c7cb00947f5a61d50d6f5f53f774.jpg", "website": "", "rating": 0.0, "rating_top": 0, "added_by_status": null, "playtime": 0, "achievements_count": 0, "ratings_count": 0, "suggestions_count": 3, "game_series_count": 0, "reviews_count": 0, "platforms": ["Web"], "developers": ["David L\u00f3pez"], "genres": [], "publishers": [], "esrb_rating": null}