{"id": 374128, "slug": "frog-shelter", "name": "Frog Shelter", "name_original": "Frog Shelter", "description": "<p>Terry the Frog has fallen from his house high atop the Amazon Rain forest\u00a0and it's up to you to help him hop back up to the top.\u00a0</p>\n<p>Make sure to seek shelter, as hungry birds will be on the lookout for your tasty frog!</p>\n\n<p>The higher you go the more spread out available shelter will become. <br/><br/></p>\n<p>Reach Terry's house to Win!</p>\n<p>Use A and D to Aim Terry left or right<br/><br/></p>\n<p>Hold-down the space bar to determine how far he hops, not pressing A or D will cause Terry to hop straight up</p>\n\n<p>Music By James Evans\u00a0</p>", "metacritic": null, "released": "2019-09-11", "tba": false, "updated": "2019-09-13T07:02:04", "background_image": "https://media.rawg.io/media/screenshots/6a7/6a7885c5c5a6342ac144180aae64194c.jpg", "website": "", "rating": 0.0, "rating_top": 0, "added_by_status": null, "playtime": 0, "achievements_count": 0, "ratings_count": 0, "suggestions_count": 55, "game_series_count": 0, "reviews_count": 0, "platforms": ["Web"], "developers": ["Wolfspear"], "genres": ["Platformer"], "publishers": [], "esrb_rating": null}