{"id": 490216, "slug": "fall-2020-projects-vr", "name": "Fall 2020 projects-VR", "name_original": "Fall 2020 projects-VR", "description": "<p>deGeim, Made by Lassi Jylh\u00e4nkangas. For Oculus.\u00a0 Video:</p>\n\n<p>Bigfoot Related Plane Crash Survival Simulator, Made by Elias Ahlgr\u00e9n. For Oculus. Video:</p>\n\n<p>Office Simulator, Made by William Rueter and Josef Solonen. SteamVR. Gameplay video coming soon.<br/></p>\n<p>Woodcut, made by Niko Nieminen and Kasperi Klaavu. Steam VR. Gameplay video:</p>", "metacritic": null, "released": "2020-09-04", "tba": false, "updated": "2020-09-07T06:10:25", "background_image": "https://media.rawg.io/media/screenshots/fdc/fdccce1d517d6a53d3cc77b4e323b473.jpg", "website": "", "rating": 0.0, "rating_top": 0, "added_by_status": null, "playtime": 0, "achievements_count": 0, "ratings_count": 0, "suggestions_count": 9, "game_series_count": 0, "reviews_count": 0, "platforms": ["PC"], "developers": ["stadinao"], "genres": [], "publishers": [], "esrb_rating": null}