{"id": 507168, "slug": "tower-of-mice", "name": "Tower of Mice", "name_original": "Tower of Mice", "description": "Take the role as Ria in this Roguelite inspired adventure. Play randomized levels in both night and day-time in the mysterious forest Abberon. Reach the mythical tower that's said to hold grand treasures. Strategically choose your battles with monsters in closed arenas. Face them in their own world through randomized platform levels. Gain experience that permanently rewards magic points and spend them on new abilities found in-game. Collect tokens and spend them on useful items to facilitate your adventure. Play through the story divided into chapters and undercover the truth about the forest Abberon och the tower.", "metacritic": null, "released": "2020-10-16", "tba": false, "updated": "2020-10-19T02:13:50", "background_image": "https://media.rawg.io/media/screenshots/5a7/5a799b28941dc5b5e02d1b341fdfef64.jpg", "website": "https://agilesoftworks.com/towerofmice-2/", "rating": 0.0, "rating_top": 0, "added_by_status": null, "playtime": 0, "achievements_count": 0, "ratings_count": 0, "suggestions_count": 239, "game_series_count": 0, "reviews_count": 0, "platforms": ["PC"], "developers": ["Agile Softworks"], "genres": ["Action", "Adventure", "RPG", "Indie"], "publishers": ["Agile Softworks"], "esrb_rating": null}