{"id": 522917, "slug": "aimtraining-imacytv23", "name": "AimTraining (iMACYTV23)", "name_original": "AimTraining (iMACYTV23)", "description": "<p>My game is FPS Aim Training, for people who wants to get there aim better. You can try my game. Its has Easy Difficulty For Begginers, Medium For Good Players, Hard For Awesome Players. The only gun you can use is Ak- 47 but it will act as a Pistol, and cannot turn to fully automatic. The Game is Made On Unreal Engine.</p>\n<p>YouTube Channel: https://www.youtube.com/c/AiMAC23</p>\n\n<p>Recommended Requirements</p>\n<p>OS: Windows 10 64 bit</p>\n<p>Processor:\u00a0Quad-core Intel or AMD, 2.5 GHz or faster</p>\n<p>Memory: 8GB ram</p>\n<p>Video Card/DirectX Version:\u00a0DirectX 11 or DirectX 12 compatible graphics card</p>", "metacritic": null, "released": "2020-11-20", "tba": false, "updated": "2020-11-23T07:13:32", "background_image": "https://media.rawg.io/media/screenshots/52f/52f27bd5a9baf19091866b168418a8b5.jpg", "website": "", "rating": 0.0, "rating_top": 0, "added_by_status": null, "playtime": 0, "achievements_count": 0, "ratings_count": 0, "suggestions_count": 95, "game_series_count": 0, "reviews_count": 0, "platforms": ["PC"], "developers": ["iMACYTV23"], "genres": ["Shooter"], "publishers": [], "esrb_rating": null}