{"id": 550020, "slug": "archeologist-simulator-2021", "name": "Archeologist simulator 2021", "name_original": "Archeologist simulator 2021", "description": "<p>You must found more artifact than your enemy.</p>\n<p>Destroy or steal enemy's artifacts is possible.</p>\n<p>Player one keys :<br/>Move : Arrow up, down, left, right\u00a0<br/>Dig artifact : spam \"space\"<br/>Destroy artifact ( must be already dug) : \"space\"<br/>Take artifact and drop into the truck : \"B\"<br/>Dash : \"N\"</p>\n<p>Player two keys :<br/>Move :\u00a0 ZQSD\u00a0<br/>Dig artifact : spam \"C\"<br/>Destroy artifact ( must be already dug) : \"C\"<br/>Take artifact and drop into the truck : \"X\"<br/>Dash : \"A\"</p>\n<p>Progamming\u00a0: Damien Benloukil</p>\n<p>Design : L\u00e9andre Renouard</p>", "metacritic": null, "released": "2021-01-31", "tba": false, "updated": "2021-02-01T04:07:27", "background_image": "https://media.rawg.io/media/screenshots/d43/d435eae553e2a5de7e517f8c29e5b7cd.jpg", "website": "", "rating": 0.0, "rating_top": 0, "added_by_status": null, "playtime": 0, "achievements_count": 0, "ratings_count": 0, "suggestions_count": 24, "game_series_count": 0, "reviews_count": 0, "platforms": ["Web"], "developers": ["LeandreRenouard"], "genres": [], "publishers": [], "esrb_rating": null}