{"id": 567567, "slug": "platformer-gdevelop", "name": "Platformer GDevelop", "name_original": "Platformer GDevelop", "description": "<p>Platformer GDevelop is a game developed by noahhguidry. It came out on 02-03-2021. <br>You can play Platformer GDevelop on Web. The game is sold via itch.io. </p>\n\n<p></p>", "metacritic": null, "released": "2021-03-02", "tba": false, "updated": "2021-03-05T10:05:18", "background_image": "https://media.rawg.io/media/screenshots/e4a/e4a708ee485c816b45583e45b7baa3ed.jpg", "website": "", "rating": 0.0, "rating_top": 0, "added_by_status": null, "playtime": 0, "achievements_count": 0, "ratings_count": 0, "suggestions_count": 6, "game_series_count": 0, "reviews_count": 0, "platforms": ["Web"], "developers": ["noahhguidry"], "genres": [], "publishers": [], "esrb_rating": null}