{"id": 624299, "slug": "wanderer-tacitus47", "name": "Wanderer (Tacitus47)", "name_original": "Wanderer (Tacitus47)", "description": "<p><strong>The presentation page is currently being created.</strong><br/></p>\n<p>A game project made by Studio M Lyon's\u00a03rd year students in 6 months.</p>\n<p>Staff :</p>\n<p>Aur\u00e9lien COMNOS : 3D Artist\u00a0<br/>https://aurelien_comnos.artstation.com/</p>\n<p>Ga\u00ebtan IORIO : 3D Artist/Rigger\u00a0<br/>https://www.artstation.com/gaetaniorio</p>\n<p>Hugo JACQUIER : 3D Artist\u00a0<br/>https://hugojacquier.artstation.com/</p>\n<p>Gabriel LUNVEN :\u00a03D Artist/Concept Artist\u00a0<br/>https://keyf0x.artstation.com/</p>\n<p>Cl\u00e9mence LEPROULT : Sound Designer <br/>http://www.clemenceleproult.fr/</p>\n<p>Corentin MERVILLE : Developer/3D Artist/Producer\u00a0<br/>https://tacitus.artstation.com/</p>\n<p>Lucas MORCILLO : 3D Artist</p>\n<p>Th\u00e9o PACALET : Game Designer/Narrative Designer/Assist Producer<br/>https://theopacalet4.wixsite.com/theopacalet</p>\n<p>Valentin PARIS : 3D Artist/Concept Artist/3D Animator <br/>Instagram :\u00a0@valentin_pariss</p>\n<p>Quentin VUGLIANO : Concept Artist/2D Animator\u00a0https://www.artstation.com/vaalanar</p>", "metacritic": null, "released": "2021-06-14", "tba": false, "updated": "2021-06-18T11:25:40", "background_image": "https://media.rawg.io/media/screenshots/740/740906255469dcf292b752b53d818cd0.jpg", "website": "", "rating": 0.0, "rating_top": 0, "added_by_status": null, "playtime": 0, "achievements_count": 0, "ratings_count": 0, "suggestions_count": 124, "game_series_count": 0, "reviews_count": 0, "platforms": ["PC"], "developers": ["Tacitus47"], "genres": ["Adventure", "Puzzle"], "publishers": [], "esrb_rating": null}