{"id": 641006, "slug": "dungeons-of-divination", "name": "Dungeons of Divination", "name_original": "Dungeons of Divination", "description": "<p><strong>Dungeons of Divination is a no-DM competitive or solo TTRPG dungeon crawl for 1-6 players utilizing a deck of tarot cards and a set of dice. Players explore a randomly generated dungeon: rooms containing both dangerous foes and valuable treasures are represented by the 22 major arcana cards placed face-down and arranged to form a grid based board. Character equipment is represented by a hand of cards from the 56 minor arcana. Turn-based combat is powered by familiar dice rolling goodness. The first player to collect 100 gold and exit the dungeon wins!</strong></p>\n<p>Made for One-Page RPG Jam 2021.</p>", "metacritic": null, "released": "2021-07-24", "tba": false, "updated": "2021-07-26T06:33:44", "background_image": "https://media.rawg.io/media/screenshots/80f/80f8df46d9f2761be49a5f4ea24164fb.jpg", "website": "", "rating": 0.0, "rating_top": 0, "added_by_status": null, "playtime": 0, "achievements_count": 0, "ratings_count": 0, "suggestions_count": 44, "game_series_count": 0, "reviews_count": 0, "platforms": ["PC"], "developers": ["rezajamesahmed"], "genres": ["Adventure", "RPG"], "publishers": [], "esrb_rating": null}