{"id": 646666, "slug": "an-offer-you-cannot-refuse", "name": "An offer you cannot refuse", "name_original": "An offer you cannot refuse", "description": "<p>English description<br/></p>\n<p>An offer you cannot refuse is a short point &amp; click adventure about group of heroes lost in the mysterious forest. Game is finished (with some bugs possible), but currently available only in slovak\u00a0language. I plan to do english translation too, but\u00a0now\u00a0I\u00a0am\u00a0not able to tell, how long it could take to be done. I have used a lot of assets from itch.io,\u00a0 links to them and their authors are listed in  Credits text file in game folder and even here on page, under the slovak description.</p>\n\n<p>Slovensk\u00fd popis<br/></p>\n<p>Ponuka, ktor\u00e1 sa neodmieta je kr\u00e1tka point &amp; click advent\u00fara o skupine dobrodruhov, straten\u00fdch v tajomnom lese. Hru netreba in\u0161talova\u0165, sta\u010d\u00ed len rozbali\u0165 stiahnut\u00fd arch\u00edv a vo vzniknutej zlo\u017eke spusti\u0165 s\u00fabor Ponuka, ktor\u00e1 sa neodmieta.exe. Rovnako sta\u010d\u00ed vyhodi\u0165 zlo\u017eku do ko\u0161a, ke\u010f u\u017e chcete hru odstr\u00e1ni\u0165. Jedn\u00e1 sa o klasick\u00fa advent\u00faru, kedy prav\u00fdm tla\u010d\u00edtkom my\u0161i sk\u00famate interakt\u00edvne miesta a \u013eav\u00fdm tla\u010d\u00edtkom s nimi interagujete. Invent\u00e1r hrdinu, z ktor\u00e9ho je mo\u017en\u00e9 vybera\u0165 z\u00edskan\u00e9 predmety, \u010di ich vz\u00e1jomne kombinova\u0165, sa nach\u00e1dza v hornej \u010dasti obrazovky, kedy vybehne, akon\u00e1hle sa k nemu pribl\u00ed\u017eite my\u0161ou. Hra je dostupn\u00e1 zadarmo a bola vytvoren\u00e1 len pomocou vo\u013ene dostupn\u00e9ho softv\u00e9ru, assetov, fontu a hudby. Linky na pou\u017eit\u00e9 s\u00fa\u010dasti od in\u00fdch autorov, sa nach\u00e1dzaj\u00fa v textovom s\u00fabore v zlo\u017eke s hrou, ako aj tu na str\u00e1nke.</p>\n\n<p>Hra moment\u00e1lne obsahuje jeden gamebreaking bug, kedy spadne pri pokuse vyrobi\u0165 \u0161\u00edpy na obrazovke s vlkom. Akon\u00e1hle budem m\u00f4c\u0165, oprav\u00edm ho, zatia\u013e je ale hra bez probl\u00e9mov dohrate\u013en\u00e1, ke\u010f \u0161\u00edpy vyrob\u00edte v t\u00e1bore. <br/></p>\n\n<p>Third party parts of the game:</p>\n<p>Engine:</p>\n<p>Adventure Game Studio <br/></p>\n<p>https://www.adventuregamestudio.co.uk/<br/></p>\n<p>https://www.adventuregamestudio.co.uk/site/ags/legal/<br/></p>\n<p>Graphics:</p>\n<p>Krita <br/></p>\n<p>https://krita.org/en/<br/></p>\n<p>Graphical assets:</p>\n<p>https://sanctumpixel.itch.io/forest-lite-pixel-art-tileset</p>\n<p>https://edermunizz.itch.io/free-pixel-art-forest</p>\n<p>https://kronbits.itch.io/backgrounds</p>\n<p>https://aeynit.itch.io/</p>\n<p>https://ragewortt.itch.io/</p>\n<p>https://pipoya.itch.io/pipoya-free-2d-game-character-sprites</p>\n<p>https://free-game-assets.itch.io/free-cartoon-forest-2d-backgrounds</p>\n<p>https://kalponic-studio.itch.io/side-scroller-village-tileset</p>\n<p>https://psychronic.itch.io/galacti-chrons-sci-fi-warehouse-tileset</p>\n<p>https://oco.itch.io/medieval-fantasy-props-pack</p>\n<p>https://vertexfrog.itch.io/free-stylised-fantasy-weapons</p>\n<p>https://free-game-assets.itch.io/free-fairy-tale-2d-backgrounds</p>\n<p>https://crazybirdladygames.itch.io/pixel-tavern-inn</p>\n<p>https://vilelarts.itch.io/pack-wood-assets</p>\n<p>https://pixabay.com/sk/vectors/klob%C3%A1sa-gril-hot-dog-m%C3%A4so-grillgut-4790...</p>\n<p>https://pixabay.com/sk/vectors/lektvary-f%C4%BEa%C5%A1e-kvapaliny-sklo-5650263/</p>\n<p>https://pixabay.com/sk/vectors/%C4%8Daj-kanvice-pi%C5%A5-poh%C3%A1r-bylinky-5624...</p>\n<p>https://pixabay.com/sk/illustrations/fazu%C4%BEa-pan-mexick%C3%A1-zemiaky-529216...</p>\n<p>https://pixabay.com/sk/illustrations/dub-vetva-akvarel-izolovan%C3%BD-2121412/</p>\n<p>https://pixabay.com/sk/vectors/chalupa-dreven%C3%A9-dom-mal%C3%A9-chaty-575902/</p>\n<p>https://pixabay.com/sk/illustrations/okn%C3%A1-sklo-tehly-%C5%BEal%C3%BAzie-kost...</p>\n<p>https://pixabay.com/sk/vectors/krb-kame%C5%88-r%C3%ADmsa-tepla-teplo-575993/</p>\n<p>https://pixabay.com/sk/illustrations/schody-schodisko-drevo-kroky-4448428/</p>\n<p>https://pixabay.com/sk/vectors/plot-zlomen%c3%bd-demon%c5%a1tr%c3%a1cia-hned%c3%...</p>\n<p>https://pixabay.com/sk/vectors/bush-zelen%c3%a1-ker-tr%c3%a1va-svie%c5%bei-57551...</p>\n<p>https://pixabay.com/sk/vectors/ru%c5%bee-strom-bush-kvety-pr%c3%adroda-576064/</p>\n<p>https://pixabay.com/sk/illustrations/kvety-kvet-kr%c3%adky-fialov%c3%a9-kvety-46...</p>\n<p>https://pixabay.com/sk/illustrations/modr%c3%a1-hortenzie-bush-kvety-2072751/</p>\n<p>https://pixabay.com/sk/vectors/prevodov%c3%a9-mechanika-nastavenia-icon-1119298/</p>\n<p>https://pixabay.com/sk/illustrations/uhlie-%c4%8dierna-tmav%c3%a1-gril-ohe%c5%88...</p>\n<p>https://pixabay.com/sk/vectors/pivo-pena-sklo-hrn%c4%8dek-za-studena-311090/</p>\n<p>Font:<br/></p>\n<p>https://fonts.google.com/specimen/Open+Sans?query=open+sans<br/></p>\n<p>Music:<br/></p>\n\n<p>https://invadableharmony.itch.io/free-game-music-pack</p>\n<p>https://invadableharmony.itch.io/</p>", "metacritic": null, "released": "2021-08-08", "tba": false, "updated": "2021-08-09T04:25:33", "background_image": "https://media.rawg.io/media/screenshots/8f9/8f9a692477c0f3f64b3f21367cbd337d.jpg", "website": "", "rating": 0.0, "rating_top": 0, "added_by_status": null, "playtime": 0, "achievements_count": 0, "ratings_count": 0, "suggestions_count": 39, "game_series_count": 0, "reviews_count": 0, "platforms": ["PC"], "developers": ["de Bielawa"], "genres": ["Adventure"], "publishers": [], "esrb_rating": null}