{"id": 659399, "slug": "explorers-sea", "name": "Explorer's sea", "name_original": "Explorer's sea", "description": "<p>You are a boat trying to lift the curst of infinitly growing</p><p>if u get stuck restart the game\u00a0</p><p>I did not make a restarting butons yet</p>", "metacritic": null, "released": "2021-08-22", "tba": false, "updated": "2021-09-08T12:35:41", "background_image": "https://media.rawg.io/media/screenshots/230/230a3a2597c4634fe5a0ea866a0c8544.jpg", "website": "", "rating": 0.0, "rating_top": 0, "added_by_status": null, "playtime": 0, "achievements_count": 0, "ratings_count": 0, "suggestions_count": 24, "game_series_count": 0, "reviews_count": 0, "platforms": ["PC", "macOS", "Linux"], "developers": ["FatBaor"], "genres": ["Adventure"], "publishers": [], "esrb_rating": null}