{"id": 723825, "slug": "bens-card-game", "name": "Ben's Card Game", "name_original": "Ben's Card Game", "description": "<p>Tired of playing the same old card packs or having to pay for new ones?\r\n  </p>\n<p>Ben\u2019s Card Game lets players create and share their own fun and unique card games.\r\n  </p>\n<p>Build your own card packs with our custom variables to have exciting and dynamic gameplay!\r\n</p>", "metacritic": null, "released": "2022-01-14", "tba": false, "updated": "2022-01-17T07:42:42", "background_image": "https://media.rawg.io/media/screenshots/802/802f5ea58bc83e15fce2eaa845097b1b.jpg", "website": "", "rating": 0.0, "rating_top": 0, "added_by_status": null, "playtime": 0, "achievements_count": 0, "ratings_count": 0, "suggestions_count": 26, "game_series_count": 0, "reviews_count": 0, "platforms": ["PC"], "developers": ["benignben"], "genres": [], "publishers": [], "esrb_rating": null}