{"id": 725888, "slug": "swaid-the-blob", "name": "Swaid the Blob", "name_original": "Swaid the Blob", "description": "<p>This is Swaid the Blob a game where you play as Swaid and must defeat the evil giant blob named Giaree. You fight enemy blobs name Gary and must get 70 kills to spawn the boss fight. You can use between Short sword and Katana to Uzi and Pistol.<br/></p>\n<p>Hop into the game you don't even have to download it(you can if you want to)<br/>it is play in browser.</p>", "metacritic": null, "released": "2022-01-24", "tba": false, "updated": "2022-01-24T04:03:45", "background_image": "https://media.rawg.io/media/screenshots/e39/e39ea541b0f97c9780d8531c408a7019.jpg", "website": "", "rating": 0.0, "rating_top": 0, "added_by_status": null, "playtime": 0, "achievements_count": 0, "ratings_count": 0, "suggestions_count": 42, "game_series_count": 0, "reviews_count": 0, "platforms": ["PC", "macOS", "Linux", "Web"], "developers": ["SixGames"], "genres": ["Shooter"], "publishers": [], "esrb_rating": null}