{"id": 785248, "slug": "treasurable-troubles", "name": "Treasurable Troubles", "name_original": "Treasurable Troubles", "description": "<p>Treasurable Troubles is an adventure game developed by RadioactiveAnt7. It came out on 09-05-2022. <br>You can play Treasurable Troubles on PC. You can purchase the game on itch.io. </p>\n\n<p></p>", "metacritic": null, "released": "2022-05-09", "tba": false, "updated": "2022-05-13T17:03:00", "background_image": "https://media.rawg.io/media/screenshots/f63/f63a5d00e1a38bf790eebf9b4abfcea5.jpg", "website": "", "rating": 0.0, "rating_top": 0, "added_by_status": null, "playtime": 0, "achievements_count": 0, "ratings_count": 0, "suggestions_count": 36, "game_series_count": 0, "reviews_count": 0, "platforms": ["PC"], "developers": ["RadioactiveAnt7"], "genres": ["Adventure"], "publishers": [], "esrb_rating": null}