{"id": 872771, "slug": "the-best-builder", "name": "The Best Builder", "name_original": "The Best Builder", "description": "<p>movement - WASD</p>\n<p>In the battle you make a body, then you CAN add\u00a0attachments or buy extra shots. You shoot with the shoot button, causing you to deal the damage amount * the among of shots you have. Heal gives you hp, and is free. While ULT heal, gives you 5 hp, for the price of $15.<br/></p>\n<p>Sry, but this is my first completed game.<br/></p>", "metacritic": null, "released": "2022-10-24", "tba": false, "updated": "2022-10-28T15:50:10", "background_image": "https://media.rawg.io/media/screenshots/78c/78c05b346a91654d18c1f379910ac5e4.jpg", "website": "", "rating": 0.0, "rating_top": 0, "added_by_status": null, "playtime": 0, "achievements_count": 0, "ratings_count": 0, "suggestions_count": 10, "game_series_count": 0, "reviews_count": 0, "platforms": ["Web"], "developers": ["Snaki boi"], "genres": ["Strategy"], "publishers": [], "esrb_rating": null}