{"id": 884506, "slug": "sisters-basics-in-make-up-and-cats", "name": "sisters basics in make up and cats", "name_original": "sisters basics in make up and cats", "description": "<p>sisters basics in make up and cats is an educational adventure game developed by cool guy1234. It was originally released in 2022. <br>You can play sisters basics in make up and cats on PC. The game is sold via itch.io. </p>\n\n<p></p>", "metacritic": null, "released": "2022-11-16", "tba": false, "updated": "2022-11-21T16:23:59", "background_image": "https://media.rawg.io/media/screenshots/878/878232fbe9585ff9c74835df70da413f.jpg", "website": "", "rating": 0.0, "rating_top": 0, "added_by_status": null, "playtime": 0, "achievements_count": 0, "ratings_count": 0, "suggestions_count": 8, "game_series_count": 0, "reviews_count": 0, "platforms": ["PC"], "developers": ["cool guy1234"], "genres": ["Adventure", "Educational"], "publishers": [], "esrb_rating": null}