{"id": 889078, "slug": "arcrow-act-icrow-of-steppes", "name": "Arcrow Act ICrow of steppes", "name_original": "Arcrow Act ICrow of steppes", "description": "<p>Esta \u00e9 a vers\u00e3o para testes, esta sendo atualizada toda semana, mas com Gunnar liberado o vai e a miss\u00e3o na ilha de treinamento e com drizel dentro da caverna de treinamento j\u00e1 pode entrar na Umbra.</p>", "metacritic": null, "released": "2022-11-29", "tba": false, "updated": "2022-12-02T16:04:44", "background_image": "https://media.rawg.io/media/screenshots/9b8/9b8e368427f8e38cf2a80fdab70e162f.jpg", "website": "", "rating": 0.0, "rating_top": 0, "added_by_status": null, "playtime": 0, "achievements_count": 0, "ratings_count": 0, "suggestions_count": 401, "game_series_count": 0, "reviews_count": 0, "platforms": ["PC"], "developers": ["Arcrow"], "genres": ["Adventure"], "publishers": [], "esrb_rating": null}